MANIFEST.in
README.rst
setup.py
XIOFileChecker/XIOFileChecker.py
XIOFileChecker/__init__.py
XIOFileChecker/context.py
XIOFileChecker/handler.py
XIOFileChecker.egg-info/PKG-INFO
XIOFileChecker.egg-info/SOURCES.txt
XIOFileChecker.egg-info/dependency_links.txt
XIOFileChecker.egg-info/entry_points.txt
XIOFileChecker.egg-info/not-zip-safe
XIOFileChecker.egg-info/top_level.txt
XIOFileChecker/utils/__init__.py
XIOFileChecker/utils/constants.py
XIOFileChecker/utils/custom_exceptions.py
XIOFileChecker/utils/misc.py