Metadata-Version: 1.2
Name: XIOFileChecker
Version: 0.3.3
Summary: Tool to compare XIOS input and output
Home-page: https://github.com/prodiguer/IOCheck
Author: Levavasseur Guillaume
Author-email: glipsl@ipsl.fr
License: UNKNOWN
Platform: Unix
Classifier: Development Status :: 5 - Production/Stable
Classifier: Environment :: Console
Classifier: Intended Audience :: Science/Research
Classifier: Intended Audience :: System Administrators
Classifier: Natural Language :: English
Classifier: Operating System :: Unix
Classifier: Programming Language :: Python
Classifier: Topic :: Scientific/Engineering
Classifier: Topic :: Software Development :: Build Tools
Requires-Python: >=2.7, <3.0
